mazemastery/__init__.py
mazemastery/api.py
mazemastery/debug_menu.py
mazemastery/maze.py
mazemastery/renderer.py
mazemastery/state.py
mazemastery/styles.py
mazemastery/types.py
mazemastery/sprites/cloud_e.png
mazemastery/sprites/cloud_n.png
mazemastery/sprites/cloud_ne.png
mazemastery/sprites/cloud_ne_inner_corner.png
mazemastery/sprites/cloud_ne_inner_corner_e.png
mazemastery/sprites/cloud_ne_inner_corner_n.png
mazemastery/sprites/cloud_nw.png
mazemastery/sprites/cloud_nw_inner_corner.png
mazemastery/sprites/cloud_nw_inner_corner_e.png
mazemastery/sprites/cloud_nw_inner_corner_n.png
mazemastery/sprites/cloud_nw_inner_corner_w.png
mazemastery/sprites/cloud_s.png
mazemastery/sprites/cloud_s_seam.png
mazemastery/sprites/cloud_se.png
mazemastery/sprites/cloud_se_inner_corner.png
mazemastery/sprites/cloud_se_inner_corner_e.png
mazemastery/sprites/cloud_se_inner_corner_s.png
mazemastery/sprites/cloud_se_spec.png
mazemastery/sprites/cloud_sw.png
mazemastery/sprites/cloud_sw_inner_corner.png
mazemastery/sprites/cloud_sw_inner_corner_s.png
mazemastery/sprites/cloud_sw_inner_corner_w.png
mazemastery/sprites/cloud_sw_spec.png
mazemastery/sprites/cloud_w.png
mazemastery/sprites/minotaur.png
mazemastery/sprites/warrior_down.png
mazemastery/sprites/warrior_left.png
mazemastery/sprites/warrior_right.png
mazemastery/sprites/warrior_up.png
mazemastery-1.0.5.dist-info/METADATA
mazemastery-1.0.5.dist-info/WHEEL
mazemastery-1.0.5.dist-info/licenses/LICENSE
mazemastery-1.0.5.dist-info/RECORD
